structsvm/__init__.py
structsvm/bundle_method.py
structsvm/hamming_costs.py
structsvm/linear_costs.py
structsvm/py.typed
structsvm/soft_margin_loss.py
structsvm-0.2.0.dist-info/METADATA
structsvm-0.2.0.dist-info/WHEEL
structsvm-0.2.0.dist-info/licenses/LICENSE
structsvm-0.2.0.dist-info/RECORD
